CHANGES.txt
README.txt
buildout.cfg
setup.py
src/z3c/__init__.py
src/z3c.etree.egg-info/PKG-INFO
src/z3c.etree.egg-info/SOURCES.txt
src/z3c.etree.egg-info/dependency_links.txt
src/z3c.etree.egg-info/namespace_packages.txt
src/z3c.etree.egg-info/not-zip-safe
src/z3c.etree.egg-info/requires.txt
src/z3c.etree.egg-info/top_level.txt
src/z3c/etree/README.txt
src/z3c/etree/SETUP.cfg
src/z3c/etree/__init__.py
src/z3c/etree/doctests.py
src/z3c/etree/doctests.txt
src/z3c/etree/doctestssuccess.txt
src/z3c/etree/doctesttests.txt
src/z3c/etree/etree.py
src/z3c/etree/interfaces.py
src/z3c/etree/testing.py
src/z3c/etree/tests.py
src/z3c/etree/z3c.etree-configure.zcml