Metadata-Version: 1.0
Name: z3c.etree
Version: 0.9.2
Summary: Abstracts out the implementation of elementtree behind the zope component architecture. And provides helper functions for testing XML output in tests.
Home-page: http://svn.zope.org/z3c.etree
Author: Michael Kerrin
Author-email: michael.kerrin@openapp.ie
License: ZPL
Platform: UNKNOWN
Classifier: Topic :: Software Development :: Testing
Classifier: Intended Audience :: Developers
Classifier: License :: OSI Approved :: Zope Public License
Classifier: Programming Language :: Python
Classifier: Framework :: Zope3
